{
  "version": "experimental",
  "tags": [
    {
      "name": "mars-textarea",
      "path": "./mars-textarea.ts",
      "description": "# <mars-textarea>\nWeb component that allows us to show an accessible and beautiful textarea so that users can interact\n\n## Installation\n```bash\n  npm i @web-inmars/mars-textarea --save\n```\n\n## Usage\n```html\n<script type=\"module\">\n   import 'mars-textarea/mars-textarea.js';\n</script>\n\n<mars-textarea>\n     Click me!\n</mars-textarea>\n```",
      "attributes": [
        {
          "name": "value",
          "type": "string",
          "default": "\"\""
        },
        {
          "name": "name",
          "type": "string",
          "default": "\"\""
        },
        {
          "name": "for",
          "type": "string",
          "default": "\"\""
        },
        {
          "name": "variant",
          "type": "string",
          "default": "\"\""
        },
        {
          "name": "caption",
          "type": "string",
          "default": "\"\""
        },
        {
          "name": "label",
          "type": "string",
          "default": "\"\""
        },
        {
          "name": "disabled",
          "type": "boolean",
          "default": "false"
        },
        {
          "name": "show-caption",
          "type": "boolean",
          "default": "false"
        }
      ],
      "properties": [
        {
          "name": "value",
          "attribute": "value",
          "type": "string",
          "default": "\"\""
        },
        {
          "name": "name",
          "attribute": "name",
          "type": "string",
          "default": "\"\""
        },
        {
          "name": "for",
          "attribute": "for",
          "type": "string",
          "default": "\"\""
        },
        {
          "name": "variant",
          "attribute": "variant",
          "type": "string",
          "default": "\"\""
        },
        {
          "name": "caption",
          "attribute": "caption",
          "type": "string",
          "default": "\"\""
        },
        {
          "name": "label",
          "attribute": "label",
          "type": "string",
          "default": "\"\""
        },
        {
          "name": "disabled",
          "attribute": "disabled",
          "type": "boolean",
          "default": "false"
        },
        {
          "name": "showCaption",
          "attribute": "show-caption",
          "type": "boolean",
          "default": "false"
        },
        {
          "name": "styles",
          "type": "CSSResult[]"
        }
      ],
      "events": [
        {
          "name": "on-input"
        }
      ]
    }
  ]
}